tiny_knn/__init__.py
tiny_knn/api.py
tiny_knn/cli.py
tiny_knn-0.2.0.dist-info/licenses/LICENSE
tiny_knn-0.2.0.dist-info/METADATA
tiny_knn-0.2.0.dist-info/WHEEL
tiny_knn-0.2.0.dist-info/entry_points.txt
tiny_knn-0.2.0.dist-info/top_level.txt
tiny_knn-0.2.0.dist-info/RECORD
