Metadata-Version: 2.4
Name: tiny-knn
Version: 0.2.0
Summary: A tiny KNN library for large Torch tensors.
Author-email: AmeyaP <ameya.prabhu@bethgelab.org>
License:                     GNU GENERAL PUBLIC LICENSE
Project-URL: Homepage, https://github.com/noosphaerenbauer/tiny-knn
Project-URL: Issues, https://github.com/noosphaerenbauer/tiny-knn/issues
Project-URL: Source, https://github.com/noosphaerenbauer/tiny-knn
Classifier: Programming Language :: Python :: 3
Classifier: License :: OSI Approved :: MIT License
Classifier: Operating System :: OS Independent
Requires-Python: >=3.8
License-File: LICENSE
Requires-Dist: torch>=2.1
Requires-Dist: numpy
Provides-Extra: test
Requires-Dist: pytest; extra == "test"
Dynamic: license-file
